atlas_rbm/__init__.py
atlas_rbm/_version.py
atlas_rbm/atlas.py
atlas_rbm/construct_model_from_genome_graph.py
atlas_rbm/construct_model_from_interaction_network.py
atlas_rbm/construct_model_from_metabolic_network.py
atlas_rbm/construct_model_from_sigma_specificity_network.py
atlas_rbm/export.py
atlas_rbm/simulation.py
atlas_rbm/utils.py
atlas_rbm-1.4.dist-info/LICENSE.txt
atlas_rbm-1.4.dist-info/METADATA
atlas_rbm-1.4.dist-info/WHEEL
atlas_rbm-1.4.dist-info/top_level.txt
atlas_rbm-1.4.dist-info/RECORD
